_aicspylibczi.cpython-310-darwin.so
aicspylibczi-3.3.1.dist-info/RECORD
aicspylibczi-3.3.1.dist-info/WHEEL
aicspylibczi-3.3.1.dist-info/top_level.txt
aicspylibczi-3.3.1.dist-info/METADATA
aicspylibczi-3.3.1.dist-info/licenses/LICENSE
aicspylibczi/_version.py
aicspylibczi/CziFile.py
aicspylibczi/__init__.py
aicspylibczi/types.py
