Metadata-Version: 2.4
Name: aicspylibczi
Version: 3.3.1
Summary: A python module and a python extension for Zeiss (CZI/ZISRAW) microscopy files.
Home-page: https://github.com/AllenCellModeling/aicspylibczi
Author: Jamie Sherman, Paul Watkins
Author-email: jamies@alleninstitute.org, pwatkins@gmail.com
License: GPL-3.0-or-later
Keywords: aicspylibczi,allen cell,imaging,computational biology
License-File: LICENSE
Requires-Dist: numpy>=1.14.1
Provides-Extra: test
Requires-Dist: flake8; extra == "test"
Requires-Dist: pytest; extra == "test"
Requires-Dist: pytest-cov; extra == "test"
Requires-Dist: pytest-raises; extra == "test"
Provides-Extra: dev
Requires-Dist: bump2version>=1.0.1; extra == "dev"
Requires-Dist: coverage>=5.0a4; extra == "dev"
Requires-Dist: flake8>=3.7.7; extra == "dev"
Requires-Dist: ipython>=7.5.0; extra == "dev"
Requires-Dist: myst-parser>=4.0.0; extra == "dev"
Requires-Dist: pytest>=4.3.0; extra == "dev"
Requires-Dist: pytest-cov==2.6.1; extra == "dev"
Requires-Dist: pytest-raises>=0.10; extra == "dev"
Requires-Dist: pytest-runner>=4.4; extra == "dev"
Requires-Dist: Sphinx; extra == "dev"
Requires-Dist: sphinx_rtd_theme>=0.1.2; extra == "dev"
Requires-Dist: breathe; extra == "dev"
Requires-Dist: tox>=3.5.2; extra == "dev"
Requires-Dist: twine>=1.13.0; extra == "dev"
Requires-Dist: wheel>=0.33.1; extra == "dev"
Requires-Dist: cmake; extra == "dev"
Provides-Extra: setup
Requires-Dist: pytest-runner; extra == "setup"
Provides-Extra: interactive
Requires-Dist: altair; extra == "interactive"
Requires-Dist: jupyterlab; extra == "interactive"
Requires-Dist: matplotlib; extra == "interactive"
Requires-Dist: pillow; extra == "interactive"
Provides-Extra: all
Requires-Dist: numpy>=1.14.1; extra == "all"
Requires-Dist: flake8; extra == "all"
Requires-Dist: pytest; extra == "all"
Requires-Dist: pytest-cov; extra == "all"
Requires-Dist: pytest-raises; extra == "all"
Requires-Dist: pytest-runner; extra == "all"
Requires-Dist: bump2version>=1.0.1; extra == "all"
Requires-Dist: coverage>=5.0a4; extra == "all"
Requires-Dist: flake8>=3.7.7; extra == "all"
Requires-Dist: ipython>=7.5.0; extra == "all"
Requires-Dist: myst-parser>=4.0.0; extra == "all"
Requires-Dist: pytest>=4.3.0; extra == "all"
Requires-Dist: pytest-cov==2.6.1; extra == "all"
Requires-Dist: pytest-raises>=0.10; extra == "all"
Requires-Dist: pytest-runner>=4.4; extra == "all"
Requires-Dist: Sphinx; extra == "all"
Requires-Dist: sphinx_rtd_theme>=0.1.2; extra == "all"
Requires-Dist: breathe; extra == "all"
Requires-Dist: tox>=3.5.2; extra == "all"
Requires-Dist: twine>=1.13.0; extra == "all"
Requires-Dist: wheel>=0.33.1; extra == "all"
Requires-Dist: cmake; extra == "all"
Requires-Dist: altair; extra == "all"
Requires-Dist: jupyterlab; extra == "all"
Requires-Dist: matplotlib; extra == "all"
Requires-Dist: pillow; extra == "all"
Dynamic: author
Dynamic: author-email
Dynamic: description
Dynamic: description-content-type
Dynamic: home-page
Dynamic: keywords
Dynamic: license
Dynamic: license-file
Dynamic: provides-extra
Dynamic: requires-dist
Dynamic: summary
